doodle_sdk/__init__.py
doodle_sdk/doodle_radio.py
doodle_sdk/settings.py
doodle_sdk/stats.py
doodle_sdk-0.1.4.dist-info/METADATA
doodle_sdk-0.1.4.dist-info/WHEEL
doodle_sdk-0.1.4.dist-info/top_level.txt
doodle_sdk-0.1.4.dist-info/RECORD
