Metadata-Version: 2.1
Name: doodle-sdk
Version: 0.1.4
Summary: SDK for better interfacing of Doodle Labs Radio
Home-page: https://github.com/AscendEngineering/doodle-sdk.git
Author: Andrew Wilkins
Author-email: andrew.wilkins@ascendengineer.com
Classifier: Programming Language :: Python :: 3
Classifier: License :: OSI Approved
Classifier: Operating System :: OS Independent
Requires-Python: >=3.8
Requires-Dist: requests>=2.0.0
Provides-Extra: dev
Requires-Dist: mkdocs; extra == "dev"
Requires-Dist: mkdocs-material; extra == "dev"
Requires-Dist: pytest; extra == "dev"
